pandag/__init__.py
pandag/graphml.py
pandag/nodes.py
pandag/pandag.py
pandag/plot.py
pandag-0.0.11.dist-info/AUTHORS.rst
pandag-0.0.11.dist-info/LICENSE
pandag-0.0.11.dist-info/METADATA
pandag-0.0.11.dist-info/WHEEL
pandag-0.0.11.dist-info/entry_points.txt
pandag-0.0.11.dist-info/top_level.txt
pandag-0.0.11.dist-info/RECORD
