Metadata-Version: 2.1
Name: pandag
Version: 0.0.11
Summary: Pandas DAG
Home-page: https://github.com/Mikata-Project/pandag
Author: NAGY, Attila
Author-email: nagy.attila@gmail.com
License: MIT license
Keywords: pandag
Platform: UNKNOWN
Classifier: Development Status :: 4 - Beta
Classifier: Intended Audience :: Developers
Classifier: License :: OSI Approved :: MIT License
Classifier: Natural Language :: English
Classifier: Programming Language :: Python :: 3
Classifier: Programming Language :: Python :: 3.5
Classifier: Programming Language :: Python :: 3.6
Classifier: Programming Language :: Python :: 3.7
Classifier: Programming Language :: Python :: 3.8
Requires-Python: >=3.5
License-File: LICENSE
License-File: AUTHORS.rst
Requires-Dist: Click (>=7.0)
Requires-Dist: networkx
Requires-Dist: more-itertools
Requires-Dist: numpy
